{
    "load": "Wird geladen..",
    "text1": "Hallo!",
    "text2": "Um mit der Anwendung zu arbeiten, geben Sie\ndie ersten Informationen ein",
    "text3": "Mann",
    "text4": "Junge Frau",
    "text5": "Sonstiges",
    "text6": "Wie groß bist du?",
    "text7": "Wie viel wiegen Sie?",
    "text8": "Wie alt bist du?",
    "text9": "Nächste Stufe\n1/2",

    "text10": "Nur ein bisschen",
    "text11": "Basierend auf Ihren Daten haben wir ausgewählt\nziele für dich. Sie können\nanpassen:",
    "text12": "Anzahl der Schritte",
    "text13": "Kalorien verbrannt",
    "text14": "Anzahl Kilometer",
    "text15": "Bereit!\n2/2",

    "text16": "Aktivität heute",

    "text17": "Statistiken",
    "text18": "der Tag",
    "text19": "Woche",
    "text20": "Monat",

    "text21": "Gesamt bestanden",
    "text22": "Im Durchschnitt\npro Tag",
    "text23": "Distanz",
    "text24": "Kalorien verbrannt",
    "text25": "Erfolge",

    "text26": "Erfolge",
    "text27": "Schritte abgeschlossen",
    "text28": "gefahrene Kilometer",
    "text29": "In Folge erreicht",

    "text30": "Einstellungen",
    "text31": "Werbungen ausschalten",
    "text32": "Benutzerdaten",
    "text33": "Höhe",
    "text34": "Das Gewicht",
    "text35": "Alter",
    "text36": "Schrittlänge",
    "text37": "Mann",
    "text38": "Junge Frau",
    "text39": "Sonstiges",
    "text40": "Zieleinstellungen",
    "text41": "Anzahl der Schritte",
    "text42": "Kalorien verbrennen",
    "text43": "Entfernung pro Tag",
    "text44": "Andere Einstellungen",
    "text45": "Sprache",
    "text46": "Einheiten",
    "text47": "Empfindlichkeit",
    "text48": "Benachrichtigungen",
    "text49": "Erinnerung an Ziele",
    "text50": "Benachrichtigungen melden",
    "text51": "Zurücksetzen",

    "text52": "Auswählen",
    "text54": "Metrisch",
    "text55": "Englisch",
    
    "text56": "Wählen",


    "text57": "Anzeigen entfernen",
    "text58": "aus der Anwendung", 
    "text59": "Verwenden Sie die App", 
    "text60": "insgesamt keine Werbung", 
    "text61": "190 Rubel pro Monat",
    "text62": "Zahlen",
    "text63": "Sie können das Abonnement verwalten oder abbestellen unter\njederzeit in Ihren Google Play-Kontoeinstellungen",
    "text64": "Sie können Ihr Abonnement im Abschnitt kündigen\n„Einstellungen“ > Apple ID können Sie jederzeit im Abschnitt „Apple ID“ auswählen\njedoch nicht weniger als einen Tag vor dem Verlängerungsdatum. \nDas Abonnement verlängert sich automatisch,\nbis Sie es kündigen",
    "text65": "Nutzungsbedingungen und Datenschutzbestimmungen\n",
    "text66": "an",
    "text67": "aus"

}